gql_lazy_paginator/__init__.py
gql_lazy_paginator/core.py
gql_lazy_paginator/decorators.py
gql_lazy_paginator/tests.py
gql_lazy_paginator-0.0.1.dist-info/METADATA
gql_lazy_paginator-0.0.1.dist-info/WHEEL
gql_lazy_paginator-0.0.1.dist-info/top_level.txt
gql_lazy_paginator-0.0.1.dist-info/RECORD
