Metadata-Version: 2.1
Name: gql-lazy-paginator
Version: 0.0.1
Summary: Lazy GraphQL pagination tools.
Home-page: https://github.com/TokkoLabs/services-tokkobroker/libraries/rpc-plugins/tokko_rpc
Author: Jose Salgado
Author-email: jsalgado@navent.com
License: BSD License
Platform: UNKNOWN
Classifier: Environment :: Web Environment
Classifier: Intended Audience :: Developers
Classifier: License :: OSI Approved :: BSD License
Classifier: Operating System :: OS Independent
Classifier: Programming Language :: Python
Classifier: Programming Language :: Python :: 3.8
Classifier: Topic :: Internet :: WWW/HTTP
Classifier: Topic :: Internet :: WWW/HTTP :: Dynamic Content
Requires-Dist: Django
Requires-Dist: graphene-django
Requires-Dist: graphene
